MANIFEST.in
README.rst
package.json
setup.cfg
setup.py
webdata/__init__.py
webdata/app.py
webdata.egg-info/PKG-INFO
webdata.egg-info/SOURCES.txt
webdata.egg-info/dependency_links.txt
webdata.egg-info/entry_points.txt
webdata.egg-info/requires.txt
webdata.egg-info/top_level.txt
webdata/app/fontawesome-webfont.eot
webdata/app/fontawesome-webfont.svg
webdata/app/fontawesome-webfont.ttf
webdata/app/fontawesome-webfont.woff
webdata/app/fontawesome-webfont.woff2
webdata/app/glyphicons-halflings-regular.eot
webdata/app/glyphicons-halflings-regular.svg
webdata/app/glyphicons-halflings-regular.ttf
webdata/app/glyphicons-halflings-regular.woff
webdata/app/glyphicons-halflings-regular.woff2
webdata/app/index.html
webdata/app/tests.html
webdata/app/webdata.js
webdata/app/webdata.js.map