Metadata-Version: 1.1
Name: webdata
Version: 0.0.1
Summary: Publish data on web
Home-page: https://github.com/walnutgeek/py-webdata
Author: Walnut Geek
Author-email: wg@walnutgeek.com
License: MIT
Keywords: dataframe,pandas,data,dataset,R,SAS,python
Platform: UNKNOWN
Classifier: Development Status :: 3 - Alpha
Classifier: Intended Audience :: Developers
Classifier: License :: OSI Approved :: MIT License
Classifier: Programming Language :: Python :: 2
Classifier: Programming Language :: Python :: 2.7
Classifier: Programming Language :: Python :: 3
Classifier: Programming Language :: Python :: 3.4
Classifier: Programming Language :: Python :: 3.5
